examples/__init__.py
examples/add_subtitles.py
examples/debug_converter.py
examples/debug_input.py
examples/generate_csv.py
examples/manage_streams.py
ffmpeg_streams_manager/__init__.py
ffmpeg_streams_manager-0.0.1.dist-info/DESCRIPTION.rst
ffmpeg_streams_manager-0.0.1.dist-info/METADATA
ffmpeg_streams_manager-0.0.1.dist-info/RECORD
ffmpeg_streams_manager-0.0.1.dist-info/WHEEL
ffmpeg_streams_manager-0.0.1.dist-info/metadata.json
ffmpeg_streams_manager-0.0.1.dist-info/top_level.txt
tests/__init__.py
tests/test_models.py
